Metadata-Version: 2.1
Name: django-clear-tables
Version: 0.1.2
Summary: django manage.py task that clears the content of the django Permission and ContentTypes tables, after an initial migration, to make manage.py loaddata work.
Home-page: https://github.com/defgsus/django-clear-tables
Author: Stefan Berke
Author-email: s.berke@netzkolchose.de
License: MIT
Platform: UNKNOWN
